windmillworkspacev1/__init__.py
windmillworkspacev1/client/__init__.py
windmillworkspacev1/client/workspace_client.py
windmill_workspace-1.0.0.2.dist-info/METADATA
windmill_workspace-1.0.0.2.dist-info/WHEEL
windmill_workspace-1.0.0.2.dist-info/top_level.txt
windmill_workspace-1.0.0.2.dist-info/RECORD
